zendeskhc/HelpCenter.py
zendeskhc/ZendeskBase.py
zendeskhc/__init__.py
zendeskhc-0.4.1.dist-info/DESCRIPTION.rst
zendeskhc-0.4.1.dist-info/METADATA
zendeskhc-0.4.1.dist-info/RECORD
zendeskhc-0.4.1.dist-info/WHEEL
zendeskhc-0.4.1.dist-info/metadata.json
zendeskhc-0.4.1.dist-info/top_level.txt
