Metadata-Version: 2.0
Name: zendeskhc
Version: 0.4.1
Summary: Python module for interacting with the Zendesk Help Center API
Home-page: https://github.com/squidboylan/zendeskpy
Author: Caleb Boylan
Author-email: calebboylan@gmail.com
License: UNKNOWN
Platform: UNKNOWN
Classifier: Development Status :: 3 - Alpha
Classifier: Intended Audience :: Developers
Classifier: License :: OSI Approved :: Apache Software License
Classifier: Operating System :: POSIX :: Linux
Classifier: Programming Language :: Python
Classifier: Programming Language :: Python :: 2
Classifier: Programming Language :: Python :: 2.7
Requires-Dist: requests
